<?xml version="1.0" encoding="UTF-8"?>
<!DOCTYPE XML>
<!-- 작성자 : 이원주 -->
<!-- 작성일 : 2018-03-21 -->
<!-- 꾸미기(레이아웃)에 대한 선언 -->
<decorators defaultdir="/WEB-INF/views/decorator">
	<!-- hello에 대한 요청이 들어오면 적용시키는 레이아웃 선언 -->
	<!-- 적용시키는 매핑명 -->
	<decorator name="main" page="default_decorator.jsp">
		<pattern>/board/*</pattern>
		<pattern>/base/*</pattern> 
		<pattern>/Index/*</pattern>
		<pattern>/menuboard/*</pattern> 
		<pattern>/member/*</pattern> 
		<pattern>/leftmenuboard/*</pattern>
		
	
	</decorator>
	
		<decorator name="jehyu" page="jehyu_decorator.jsp">
			<pattern>/jehyu/*</pattern>
		</decorator>	
		<decorator name="useafter" page="useafter_decorator.jsp">
			<pattern>/useafter/*</pattern>
		</decorator>
		<decorator name="community" page="community_decorator.jsp">
			<pattern>/community/*</pattern>
		</decorator>	
		<decorator name="entertainment" page="entertainment_decorator.jsp">
			<pattern>/entertainment/*</pattern>
		</decorator>
		<decorator name="uggallary" page="uggallary_decorator.jsp">
			<pattern>/uggallary/*</pattern>
		</decorator>
		<decorator name="attendence" page="attendence_decorator.jsp">
			<pattern>/attendence/*</pattern>
		</decorator>
		<decorator name="eventzone" page="eventzone_decorator.jsp">
			<pattern>/eventzone/*</pattern>
		</decorator>
		<decorator name="servicecenter" page="servicecenter_decorator.jsp">
			<pattern>/servicecenter/*</pattern>
		</decorator>
		<decorator name="question" page="question.jsp">
			<pattern>/question/*</pattern>
		</decorator>
		
	
<!-- 	관리자 페이지의 레이아웃 -->

<!-- 	<decorator name="admin" page="admin_decorator.jsp"> -->
<!-- 		<pattern>/admin/*</pattern> -->
<!-- 	</decorator> -->
	<!-- 게시판의 대한 요청 레이아웃 선언 -->

	<!-- 데코레이션에서 제외되는 요청을 선언 -->
</decorators>